README.md
setup.py
PythonHiringTest.egg-info/PKG-INFO
PythonHiringTest.egg-info/SOURCES.txt
PythonHiringTest.egg-info/dependency_links.txt
PythonHiringTest.egg-info/top_level.txt
python_hiring_test/__init__.py
python_hiring_test/run.py