Metadata-Version: 1.0
Name: PythonHiringTest
Version: 1.1
Summary: UNKNOWN
Home-page: UNKNOWN
Author: UNKNOWN
Author-email: UNKNOWN
License: Creative Commons Attribution-Noncommercial-Share Alike license
Platform: UNKNOWN
